pathkeeper/__init__.py
pathkeeper/path_keeper.py
pathkeeper-0.1.0.dist-info/METADATA
pathkeeper-0.1.0.dist-info/WHEEL
pathkeeper-0.1.0.dist-info/RECORD
