Metadata-Version: 2.3
Name: pathkeeper
Version: 0.1.0
Summary: Easy path access for Python projects
Author: Danny Stewart
Author-email: danny@stewart.cc
Requires-Python: >=3.12
Classifier: Programming Language :: Python :: 3
Classifier: Programming Language :: Python :: 3.12
Classifier: Programming Language :: Python :: 3.13
Requires-Dist: enviromancer (>=0.1.2,<0.2.0)
Requires-Dist: platformdirs (>=4.3.7,<5.0.0)
